Metadata-Version: 2.1
Name: tsatsu-email-lib
Version: 0.0.1
Summary: An email library for sending emails
Home-page: 
Author: Akorlire Edward Tsatsu
Author-email: edwardakorlie73@gmail.com
License: MIT
Keywords: email
Classifier: Development Status :: 5 - Production/Stable
Classifier: Intended Audience :: Education
Classifier: Operating System :: Microsoft :: Windows :: Windows 10
Classifier: License :: OSI Approved :: MIT License
Classifier: Programming Language :: Python :: 3
